{
"type": "FeatureCollection",
"crs": { "type": "name", "properties": { "name": "urn:ogc:def:crs:OGC:1.3:CRS84" } },
                                                                                
"features": [
{ "type": "Feature", "properties": { "name": "22_07_2015_2" }, "geometry": { "type": "Point", "coordinates": [ 85.13342180925423, 56.588114137795422] } },
{ "type": "Feature", "properties": { "name": "22_07_2015_1" }, "geometry": { "type": "Point", "coordinates": [ 85.141713314075815, 56.590824529044134] } }
]
}
